ovos_stt_plugin_azure/__init__.py
ovos_stt_plugin_azure/version.py
ovos_stt_plugin_azure-0.0.0a2.dist-info/LICENSE
ovos_stt_plugin_azure-0.0.0a2.dist-info/METADATA
ovos_stt_plugin_azure-0.0.0a2.dist-info/WHEEL
ovos_stt_plugin_azure-0.0.0a2.dist-info/entry_points.txt
ovos_stt_plugin_azure-0.0.0a2.dist-info/top_level.txt
ovos_stt_plugin_azure-0.0.0a2.dist-info/zip-safe
ovos_stt_plugin_azure-0.0.0a2.dist-info/RECORD
