Metadata-Version: 2.1
Name: ovos-stt-plugin-azure
Version: 0.0.0a2
Summary: ovos azure stt plugin for mycroft
Home-page: https://github.com/OpenVoiceOS/ovos-stt-azure-plugin
Author: JarbasAi
Author-email: jarbasai@mailfence.com
License: Apache-2.0
Keywords: mycroft OpenVoiceOS OVOS plugin stt
Platform: UNKNOWN
Classifier: Development Status :: 3 - Alpha
Classifier: Intended Audience :: Developers
Classifier: Topic :: Text Processing :: Linguistic
Classifier: License :: OSI Approved :: Apache Software License
Classifier: Programming Language :: Python :: 3.7
Classifier: Programming Language :: Python :: 3.8
Classifier: Programming Language :: Python :: 3.9
Classifier: Programming Language :: Python :: 3.10
Requires-Dist: ovos-plugin-manager (>=0.0.5)
Requires-Dist: requests
